taskq/__init__.py
taskq/cli.py
taskq/common.py
taskq/utils.py
taskq/actions/__init__.py
taskq/actions/add.py
taskq/actions/backend.py
taskq/actions/base.py
taskq/actions/config.py
taskq/actions/filter.py
taskq/actions/read.py
taskq/actions/write.py
taskq/backends/__init__.py
taskq/backends/base.py
taskq/backends/dummy.py
taskq/backends/ts.py
tsq-0.0.18.dist-info/LICENSE.md
tsq-0.0.18.dist-info/METADATA
tsq-0.0.18.dist-info/WHEEL
tsq-0.0.18.dist-info/entry_points.txt
tsq-0.0.18.dist-info/top_level.txt
tsq-0.0.18.dist-info/RECORD
