Metadata-Version: 2.1
Name: tsq
Version: 0.0.18
Summary: A Friendly Task Scheduler Frontend
Author: admk
Project-URL: Homepage, https://github.com/admk/tsq
Project-URL: Issues, https://github.com/admk/tsq/issues
Classifier: Programming Language :: Python :: 3
Classifier: License :: OSI Approved :: MIT License
Classifier: Operating System :: OS Independent
Requires-Python: >=3.8
License-File: LICENSE.md
Requires-Dist: tqdm
Requires-Dist: tomlkit
Requires-Dist: tabulate >=0.9.0
Requires-Dist: blessed >=1.20.0
